database_creatorplus/__init__.py
database_creatorplus/db_module.py
database_creatorplus-0.3.1.dist-info/METADATA
database_creatorplus-0.3.1.dist-info/WHEEL
database_creatorplus-0.3.1.dist-info/top_level.txt
database_creatorplus-0.3.1.dist-info/RECORD
