Metadata-Version: 2.4
Name: database_creatorplus
Version: 0.3.1
Summary: database creator
Author-email: vladislavkirilov2001@mail.ru
Dynamic: author-email
Dynamic: summary
